Topsis_Yuvika_102203800/__init__.py
Topsis_Yuvika_102203800/cli.py
Topsis_Yuvika_102203800/topsis.py
Topsis_Yuvika_102203800-0.3.dist-info/LICENSE.txt
Topsis_Yuvika_102203800-0.3.dist-info/METADATA
Topsis_Yuvika_102203800-0.3.dist-info/WHEEL
Topsis_Yuvika_102203800-0.3.dist-info/entry_points.txt
Topsis_Yuvika_102203800-0.3.dist-info/top_level.txt
Topsis_Yuvika_102203800-0.3.dist-info/RECORD
